sewer/__init__.py
sewer/__main__.py
sewer/acme.py
sewer/auth.py
sewer/catalog.json
sewer/catalog.py
sewer/cli.py
sewer/client.py
sewer/config.py
sewer/crypto.py
sewer/lib.py
sewer/meta.json
sewer/dns_providers/__init__.py
sewer/dns_providers/acmedns.py
sewer/dns_providers/aliyundns.py
sewer/dns_providers/auroradns.py
sewer/dns_providers/cloudflare.py
sewer/dns_providers/cloudns.py
sewer/dns_providers/common.py
sewer/dns_providers/dnspod.py
sewer/dns_providers/duckdns.py
sewer/dns_providers/gandi.py
sewer/dns_providers/hurricane.py
sewer/dns_providers/powerdns.py
sewer/dns_providers/rackspace.py
sewer/dns_providers/route53.py
sewer/dns_providers/unbound_ssh.py
sewer/providers/__init__.py
sewer/providers/demo.py
sewer-0.8.4.dist-info/LICENSE.txt
sewer-0.8.4.dist-info/METADATA
sewer-0.8.4.dist-info/WHEEL
sewer-0.8.4.dist-info/entry_points.txt
sewer-0.8.4.dist-info/top_level.txt
sewer-0.8.4.dist-info/RECORD
