Metadata-Version: 2.1
Name: sewer
Version: 0.8.4
Summary: Sewer is a programmatic Lets Encrypt(ACME) client
Home-page: https://github.com/komuw/sewer
Author: komuW
Author-email: komuw05@gmail.com
Maintainer: mmaney
License: MIT
Keywords: letsencrypt,ACME,dns-01,http-01,RFC8555
Platform: UNKNOWN
Classifier: Development Status :: 4 - Beta
Classifier: Environment :: Console
Classifier: Intended Audience :: Developers
Classifier: Topic :: Software Development :: Build Tools
Classifier: Topic :: Internet :: WWW/HTTP
Classifier: Topic :: Security
Classifier: Topic :: System :: Installation/Setup
Classifier: Topic :: System :: Networking
Classifier: Topic :: System :: Systems Administration
Classifier: Topic :: Utilities
Classifier: License :: OSI Approved :: MIT License
Classifier: Programming Language :: Python :: 3
Classifier: Programming Language :: Python :: 3.5
Classifier: Programming Language :: Python :: 3.6
Classifier: Programming Language :: Python :: 3.7
Classifier: Programming Language :: Python :: 3.8
Requires-Dist: cryptography
Requires-Dist: requests
Provides-Extra: acmedns
Requires-Dist: dnspython ; extra == 'acmedns'
Provides-Extra: aliyun
Requires-Dist: aliyun-python-sdk-alidns ; extra == 'aliyun'
Requires-Dist: aliyun-python-sdk-core-v3 ; extra == 'aliyun'
Provides-Extra: alldns
Requires-Dist: aliyun-python-sdk-alidns ; extra == 'alldns'
Requires-Dist: aliyun-python-sdk-core-v3 ; extra == 'alldns'
Requires-Dist: apache-libcloud ; extra == 'alldns'
Requires-Dist: boto3 ; extra == 'alldns'
Requires-Dist: cloudns-api ; extra == 'alldns'
Requires-Dist: dnspython ; extra == 'alldns'
Requires-Dist: hurricanedns ; extra == 'alldns'
Requires-Dist: tldextract ; extra == 'alldns'
Provides-Extra: aurora
Requires-Dist: apache-libcloud ; extra == 'aurora'
Requires-Dist: tldextract ; extra == 'aurora'
Provides-Extra: cloudflare
Provides-Extra: cloudns
Requires-Dist: cloudns-api ; extra == 'cloudns'
Provides-Extra: dev
Requires-Dist: twine ; extra == 'dev'
Requires-Dist: wheel ; extra == 'dev'
Provides-Extra: dnspod
Provides-Extra: duckdns
Provides-Extra: gandi
Provides-Extra: hurricane
Requires-Dist: hurricanedns ; extra == 'hurricane'
Provides-Extra: powerdns
Provides-Extra: rackspace
Requires-Dist: tldextract ; extra == 'rackspace'
Provides-Extra: route53
Requires-Dist: boto3 ; extra == 'route53'
Provides-Extra: test
Requires-Dist: black (==19.10b0) ; extra == 'test'
Requires-Dist: coverage (>=5.0) ; extra == 'test'
Requires-Dist: pylint (==2.3.1) ; extra == 'test'
Requires-Dist: pytest (>=6.0) ; extra == 'test'
Provides-Extra: unbound_ssh
